silero/__init__.py
silero/denoiser_utils.py
silero/silero.py
silero/tts_utils.py
silero/utils.py
silero-0.5.3.dist-info/licenses/LICENSE
silero-0.5.3.dist-info/licenses/LICENSE_CIS
silero-0.5.3.dist-info/METADATA
silero-0.5.3.dist-info/WHEEL
silero-0.5.3.dist-info/top_level.txt
silero-0.5.3.dist-info/RECORD
