Metadata-Version: 2.4
Name: silero
Version: 0.5.3
Summary: Silero Models: pre-trained enterprise-grade TTS models.
Home-page: https://github.com/snakers4/silero-models
Author: Silero Team
Author-email: hello@silero.ai
Project-URL: Bug Tracker, https://github.com/snakers4/silero-models/issues
Classifier: Intended Audience :: Developers
Classifier: Intended Audience :: Science/Research
Classifier: License :: OSI Approved :: MIT License
Classifier: Operating System :: OS Independent
Classifier: Programming Language :: Python :: 3
Classifier: Programming Language :: Python :: 3.6
Classifier: Programming Language :: Python :: 3.7
Classifier: Programming Language :: Python :: 3.8
Classifier: Programming Language :: Python :: 3.9
Classifier: Programming Language :: Python :: 3.10
Classifier: Programming Language :: Python :: 3.11
Classifier: Programming Language :: Python :: 3.12
Classifier: Programming Language :: Python :: 3.13
Classifier: Topic :: Multimedia :: Sound/Audio
Classifier: Topic :: Scientific/Engineering :: Artificial Intelligence
Requires-Python: >=3.7
License-File: LICENSE
License-File: LICENSE_CIS
Requires-Dist: torch>=1.12.0
Requires-Dist: omegaconf>=2.1.0
Dynamic: license-file
